trio_websocket/__init__.py
trio_websocket/_impl.py
trio_websocket/_version.py
trio_websocket/py.typed
trio_websocket-0.12.1.dist-info/LICENSE
trio_websocket-0.12.1.dist-info/METADATA
trio_websocket-0.12.1.dist-info/WHEEL
trio_websocket-0.12.1.dist-info/top_level.txt
trio_websocket-0.12.1.dist-info/RECORD
