Metadata-Version: 2.1
Name: trio-websocket
Version: 0.12.1
Summary: WebSocket library for Trio
Home-page: https://github.com/python-trio/trio-websocket
Author: Mark E. Haase
Author-email: mehaase@gmail.com
Project-URL: Bug Reports, https://github.com/python-trio/trio-websocket/issues
Project-URL: Source, https://github.com/python-trio/trio-websocket
Keywords: websocket client server trio
Classifier: Development Status :: 3 - Alpha
Classifier: Intended Audience :: Developers
Classifier: Topic :: Software Development :: Libraries
Classifier: License :: OSI Approved :: MIT License
Classifier: Programming Language :: Python :: 3.8
Classifier: Programming Language :: Python :: 3.9
Classifier: Programming Language :: Python :: 3.10
Classifier: Programming Language :: Python :: 3.11
Classifier: Programming Language :: Python :: 3.12
Classifier: Programming Language :: Python :: 3.13
Classifier: Programming Language :: Python :: Implementation :: CPython
Classifier: Programming Language :: Python :: Implementation :: PyPy
Classifier: Typing :: Typed
Requires-Python: >=3.8
License-File: LICENSE
Requires-Dist: exceptiongroup; python_version < "3.11"
Requires-Dist: outcome>=1.2.0
Requires-Dist: trio>=0.11
Requires-Dist: wsproto>=0.14
